article_cli/__init__.py
article_cli/__main__.py
article_cli/cli.py
article_cli/config.py
article_cli/fonts.py
article_cli/git_manager.py
article_cli/latex_compiler.py
article_cli/repository_setup.py
article_cli/themes.py
article_cli/typst_compiler.py
article_cli/zotero.py
article_cli-1.4.0.dist-info/METADATA
article_cli-1.4.0.dist-info/WHEEL
article_cli-1.4.0.dist-info/entry_points.txt
article_cli-1.4.0.dist-info/licenses/LICENSE
article_cli-1.4.0.dist-info/RECORD
