Metadata-Version: 2.4
Name: article-cli
Version: 1.4.0
Summary: CLI tool for managing LaTeX and Typst documents with git integration and Zotero bibliography
Project-URL: Homepage, https://github.com/feelpp/article.cli
Project-URL: Documentation, https://github.com/feelpp/article.cli#readme
Project-URL: Repository, https://github.com/feelpp/article.cli.git
Project-URL: Issues, https://github.com/feelpp/article.cli/issues
Author-email: Christophe Prud'homme <prudhomm@cemosis.fr>
License: MIT License
License-File: LICENSE
Keywords: academic,bibliography,git,latex,presentations,research,typst,zotero
Classifier: Development Status :: 4 - Beta
Classifier: Intended Audience :: Science/Research
Classifier: License :: OSI Approved :: MIT License
Classifier: Operating System :: OS Independent
Classifier: Programming Language :: Python :: 3
Classifier: Programming Language :: Python :: 3.8
Classifier: Programming Language :: Python :: 3.9
Classifier: Programming Language :: Python :: 3.10
Classifier: Programming Language :: Python :: 3.11
Classifier: Programming Language :: Python :: 3.12
Classifier: Topic :: Scientific/Engineering
Classifier: Topic :: Text Processing :: Markup :: LaTeX
Requires-Python: >=3.8
Requires-Dist: requests>=2.28.0
Provides-Extra: dev
Requires-Dist: black>=23.0; extra == 'dev'
Requires-Dist: flake8>=6.0; extra == 'dev'
Requires-Dist: mypy>=1.0; extra == 'dev'
Requires-Dist: pytest-cov; extra == 'dev'
Requires-Dist: pytest>=7.0; extra == 'dev'
Requires-Dist: types-requests; extra == 'dev'
